Metadata-Version: 1.1
Name: cwsharp
Version: 0.1
Summary: Chinese Words Segementations
Home-page: https://github.com/zhengchun/cwsharp-python
Author: zhengchun
Author-email: UNKNOWN
License: MIT
Keywords: NLP,tokenizing,Chinese word segementation,mmseg
Platform: Linux
Platform: Windows
Classifier: Intended Audience :: Developers
Classifier: License :: OSI Approved :: MIT License
Classifier: Operating System :: OS Independent
Classifier: Natural Language :: Chinese (Simplified)
Classifier: Programming Language :: Python
Classifier: Programming Language :: Python :: 2
Classifier: Programming Language :: Python :: 2.7
Classifier: Programming Language :: Python :: 3
Classifier: Programming Language :: Python :: 3.6
Classifier: Topic :: Text Processing
Classifier: Topic :: Text Processing :: General
